jaxley_mech/__init__.py
jaxley_mech/find_mech.py
jaxley_mech/solvers.py
jaxley_mech/utils.py
jaxley_mech/channels/__init__.py
jaxley_mech/channels/aoyama00.py
jaxley_mech/channels/benison01.py
jaxley_mech/channels/chen24.py
jaxley_mech/channels/fohlmeister97.py
jaxley_mech/channels/hodgkin52.py
jaxley_mech/channels/kamiyama09.py
jaxley_mech/channels/l5pc.py
jaxley_mech/channels/liu04.py
jaxley_mech/channels/torre90.py
jaxley_mech/channels/usui96.py
jaxley_mech/synapses/__init__.py
jaxley_mech/synapses/destexhe98.py
jaxley_mech/synapses/gap_junction.py
jaxley_mech/synapses/ribbon.py
jaxley_mech/synapses/ribbon_mGluR6.py
tests/test_init_state.py
tests/test_pickle.py
tests/test_solvers.py
tests/test_synapse_indexing.py
jaxley_mech-0.3.0.dist-info/LICENSE
jaxley_mech-0.3.0.dist-info/METADATA
jaxley_mech-0.3.0.dist-info/WHEEL
jaxley_mech-0.3.0.dist-info/top_level.txt
jaxley_mech-0.3.0.dist-info/RECORD
