Metadata-Version: 2.2
Name: jaxley-mech
Version: 0.3.0
Summary: A Jaxley-based library of ion channels and syanpses for biophysical neuron models.
Requires-Python: >=3.8.0
License-File: LICENSE
Requires-Dist: jax[cpu]
Requires-Dist: numpy
Requires-Dist: pandas
Requires-Dist: matplotlib
Requires-Dist: jaxley>=0.2.0
Requires-Dist: diffrax>=0.6
Requires-Dist: equinox>=0.11.8
Provides-Extra: dev
Requires-Dist: ruff; extra == "dev"
Requires-Dist: jupyter; extra == "dev"
Requires-Dist: ipykernel; extra == "dev"
Requires-Dist: mkdocs; extra == "dev"
Requires-Dist: mkdocs-material; extra == "dev"
Requires-Dist: markdown-include; extra == "dev"
Requires-Dist: mkdocs-redirects; extra == "dev"
Requires-Dist: mkdocstrings[python]>=0.18; extra == "dev"
Requires-Dist: neuron; extra == "dev"
Requires-Dist: pytest; extra == "dev"
Requires-Dist: pyright; extra == "dev"
Requires-Dist: watermark; extra == "dev"
Requires-Dist: tqdm; extra == "dev"
